estpop/__init__.py
estpop/simulation.py
estpop-0.0.4.dist-info/LICENSE.txt
estpop-0.0.4.dist-info/METADATA
estpop-0.0.4.dist-info/WHEEL
estpop-0.0.4.dist-info/top_level.txt
estpop-0.0.4.dist-info/RECORD
